pyproject_scripts/cli.py
pyproject_scripts-0.1.0.dist-info/licenses/LICENSE
pyproject_scripts-0.1.0.dist-info/METADATA
pyproject_scripts-0.1.0.dist-info/WHEEL
pyproject_scripts-0.1.0.dist-info/entry_points.txt
pyproject_scripts-0.1.0.dist-info/top_level.txt
pyproject_scripts-0.1.0.dist-info/RECORD
