Metadata-Version: 2.4
Name: pyproject-scripts
Version: 0.1.0
Summary: Run scripts defined in a project's pyproject.toml (like npm run)
Author-email: Oliver Kleinke <oliver.kleinke@c-01a.de>
License-Expression: AGPL-3.0-or-later
Project-URL: Homepage, https://github.com/okleinke/pyproject-scripts
Keywords: pyproject,scripts,cli
Classifier: Programming Language :: Python :: 3
Classifier: Programming Language :: Python :: 3 :: Only
Classifier: Programming Language :: Python :: 3.11
Classifier: Programming Language :: Python :: 3.12
Classifier: Programming Language :: Python :: 3.13
Classifier: Operating System :: OS Independent
Requires-Python: >=3.11
License-File: LICENSE
Provides-Extra: dev
Requires-Dist: build>=1.3.0; extra == "dev"
Requires-Dist: pytest-cov>=4.0; extra == "dev"
Requires-Dist: pytest>=8.0; extra == "dev"
Requires-Dist: ruff>=0.6.0; extra == "dev"
Dynamic: license-file
